<window>
	
	<defaultcontrol always="true">84</defaultcontrol>
	<allowoverlay>no</allowoverlay>
	
	<!--Splash Screen-->
	<onload condition="!Skin.HasSetting(NoSplashScreen)">ActivateWindow(60)</onload>
	
	<onload>ClearProperty(TVGuide.MondayList,Home)</onload>
	<onload>ClearProperty(TVGuide.TuesdayList,Home)</onload>
	<onload>ClearProperty(TVGuide.WednesdayList,Home)</onload>
	<onload>ClearProperty(TVGuide.ThursdayList,Home)</onload>
	<onload>ClearProperty(TVGuide.FridayList,Home)</onload>
	<onload>ClearProperty(TVGuide.SaturdayList,Home)</onload>
	<onload>ClearProperty(TVGuide.SundayList,Home)</onload>
	
	<controls>
	
		<control type="button" id="84">
			<onfocus>SetFocus(207)</onfocus>
			<visible allowhiddenfocus="true">false</visible>
		</control>
	
		<!--Background Area-->
		<include>Common_Background</include>
		
		<control type="group">
		
			<include>Common_Dimensions</include>
			<include>Common_Animation_Window</include>
		
			<!--Top Area-->
			<include>Common_Breadcrumb_Alt</include>
			<include>Common_Clock</include>
			<include>Common_Overlay</include>
			
			<!--Content Area-->
			<control type="group">
			
				<posx>0</posx>
				<posy>100</posy>
				<width>1280</width>
				<height>480</height>
				
				<include>Common_Animation_Content_Splash</include>
				
				<!--List-->
				<control type="group">
				
					<posx>60</posx>
					<posy>0</posy>
					<width>660</width>
					<height>480</height>
					
					<control type="label">
							
						<posx>0</posx>
						<posy>0</posy>
						<width min="20" max="530">auto</width>
						<height>100</height>
						<label>explore</label>
						<font>Menu-Scroll</font>
						<textcolor>Label_Normal</textcolor>
						<aligny>top</aligny>
						<wrapmultiline>true</wrapmultiline>
						<scrollspeed>0</scrollspeed>
						
					</control>
					
					<control type="list" id="207">
							
						<posx>0</posx>
						<posy>60</posy>
						<width>400</width>
						<height>480</height>
						<onleft>9000</onleft>
						<onright condition="StringCompare(Container(207).Position,0)">200</onright>
						<onright condition="StringCompare(Container(207).Position,1)">201</onright>
						<onright condition="StringCompare(Container(207).Position,2)">202</onright>
						<onright condition="StringCompare(Container(207).Position,3)">203</onright>
						<onright condition="StringCompare(Container(207).Position,4)">204</onright>
						<onright condition="StringCompare(Container(207).Position,5)">205</onright>
						<onright condition="StringCompare(Container(207).Position,6)">206</onright>
						<onup>207</onup>
						<ondown>207</ondown>
						<pagecontrol>60</pagecontrol>
						<viewtype label="List">list</viewtype>
						<scrolltime tween="cubic" easing="out">600</scrolltime>
						
						<itemlayout width="400" height="60">
						
							<control type="image">
							
								<posx>14</posx>
								<posy>17</posy>
								<width>26</width>
								<height>26</height>
								<texture>kai/kai_date.png</texture>
								<aspectratio>center</aspectratio>
								<colordiffuse>Label_Normal</colordiffuse>
								
								<visible>StringCompare(ListItem.Label,System.Date(DDD))</visible>
								
								<animation type="VisibleChange">
									<effect type="fade" start="0" end="100" time="400" delay="200" />
								</animation>
							
							</control>

							<control type="label">
							
								<posx>32</posx>
								<posy>0</posy>
								<width min="20" max="380">auto</width>
								<height>60</height>
								<label>$INFO[ListItem.Label]</label>
								<font>Menu-List</font>
								<textcolor>Label_Normal</textcolor>
								<selectedcolor>Label_Highlight</selectedcolor>
								<aligny>center</aligny>
								
								<animation type="Conditional" condition="StringCompare(ListItem.Label,System.Date(DDD))">
									<effect type="slide" start="0,0" end="20,0" time="400" />
								</animation>
								
							</control>
							
						</itemlayout>

						<focusedlayout width="400" height="60">

							<control type="image">
							
								<posx>0</posx>
								<posy>0</posy>
								<width>400</width>
								<height>60</height>
								<texture>colors/color_white.png</texture>
								<colordiffuse>Background_Highlight</colordiffuse>
							
							</control>
							
							<control type="image">
							
								<posx>14</posx>
								<posy>17</posy>
								<width>26</width>
								<height>26</height>
								<texture>kai/kai_date.png</texture>
								<aspectratio>center</aspectratio>
								<colordiffuse>Label_Normal</colordiffuse>
								
								<visible>StringCompare(ListItem.Label,System.Date(DDD))</visible>
								
								<animation type="VisibleChange">
									<effect type="fade" start="0" end="100" time="400" delay="200" />
								</animation>
							
							</control>
						
							<control type="label">
							
								<posx>32</posx>
								<posy>0</posy>
								<width min="20" max="380">auto</width>
								<height>60</height>
								<label>$INFO[ListItem.Label]</label>
								<font>Menu-List</font>
								<textcolor>Label_Normal</textcolor>
								<aligny>center</aligny>
								<scrollspeed>0</scrollspeed>
								
								<animation type="Conditional" condition="StringCompare(ListItem.Label,System.Date(DDD))">
									<effect type="slide" start="0,0" end="20,0" time="400" />
								</animation>
								
							</control>

						</focusedlayout>
						
						<content>
						
							<item id="1">
								<label>Monday</label>
								<onclick>Control.SetFocus(200)</onclick>
							</item>	
							
							<item id="2">
								<label>Tuesday</label>
								<onclick>Control.SetFocus(201)</onclick>
							</item>
							
							<item id="3">
								<label>Wednesday</label>
								<onclick>Control.SetFocus(202)</onclick>
							</item>
							
							<item id="4">
								<label>Thursday</label>
								<onclick>Control.SetFocus(203)</onclick>
							</item>
							
							<item id="5">
								<label>Friday</label>
								<onclick>Control.SetFocus(204)</onclick>
							</item>
							
							<item id="6">
								<label>Saturday</label>
								<onclick>Control.SetFocus(205)</onclick>
							</item>
							
							<item id="7">
								<label>Sunday</label>
								<onclick>Control.SetFocus(206)</onclick>
							</item>
							
						</content>
							
					</control>
					
				</control>
				
				<control type="label">
						
					<posx>60</posx>
					<posy>500</posy>
					<width>640</width>
					<height>64</height>
					<label>[UPPERCASE]Shows airing on this day: $VAR[TVNextAired_TotalShows][/UPPERCASE]</label>
					<font>Menu-List-Small</font>
					<textcolor>Label_Disabled</textcolor>
					<align>left</align>
					<aligny>top</aligny>
				
				</control>
			
				<control type="group">
			
					<posx>460</posx>
					<posy>0</posy>
					<width>1280</width>
					<height>480</height>
					
					<control type="label">
							
						<posx>60</posx>
						<posy>0</posy>
						<width min="20" max="530">auto</width>
						<height>100</height>
						<label>show listing</label>
						<font>Menu-Scroll</font>
						<textcolor>Label_Normal</textcolor>
						<aligny>top</aligny>
						<wrapmultiline>true</wrapmultiline>
						<scrollspeed>0</scrollspeed>
						
					</control>
					
					<control type="textbox">
							
						<posx>60</posx>
						<posy>100</posy>
						<width>1500</width>
						<height>480</height>
						<label>there are no episodes showing on this day</label>
						<font>Menu-List</font>
						<textcolor>Label_Normal</textcolor>
						<aligny>top</aligny>
						<wrapmultiline>true</wrapmultiline>
						<scrollspeed>0</scrollspeed>
						
						<visible>[IsEmpty(Container(200).ListItem(0).Label) + StringCompare(Container(207).Position,0)] | [IsEmpty(Container(201).ListItem(0).Label) + StringCompare(Container(207).Position,1)] | [IsEmpty(Container(202).ListItem(0).Label) + StringCompare(Container(207).Position,2)] | [IsEmpty(Container(203).ListItem(0).Label) + StringCompare(Container(207).Position,3)] | [IsEmpty(Container(204).ListItem(0).Label) + StringCompare(Container(207).Position,4)] | [IsEmpty(Container(205).ListItem(0).Label) + StringCompare(Container(207).Position,5)] | [IsEmpty(Container(206).ListItem(0).Label) + StringCompare(Container(207).Position,6)]</visible>
						
					</control>
					
					<!--Monday-->
					<control type="group">
					
						<width>1280</width>
						<height>480</height>
						
						<visible>!IsEmpty(Container(200).ListItem(0).Label) + StringCompare(Container(207).Position,0)</visible>
						
						<include>Common_Animation_ShowListing</include>
						
						<control type="fixedlist" id="200">
								
							<onup>207</onup>
							<ondown>207</ondown>
							<onleft>207</onleft>
							<onright>200</onright>
							<include>Common_TVNextAired_FixedList</include>

						</control>
					
					</control>			
					
					<!--Tuesday-->
					<control type="group">
						
						<width>1280</width>
						<height>480</height>
						
						<visible>!IsEmpty(Container(201).ListItem(0).Label) + StringCompare(Container(207).Position,1)</visible>
						
						<include>Common_Animation_ShowListing</include>
						
						<control type="fixedlist" id="201">
							
							<onup>207</onup>
							<ondown>207</ondown>
							<onleft>207</onleft>
							<onright>201</onright>
							<include>Common_TVNextAired_FixedList</include>

						</control>
						
					</control>
					
					<!--Wednesday-->
					<control type="group">
						
						<width>1280</width>
						<height>480</height>
						
						<visible>!IsEmpty(Container(202).ListItem(0).Label) + StringCompare(Container(207).Position,2)</visible>
						
						<include>Common_Animation_ShowListing</include>
						
						<control type="fixedlist" id="202">
								
							<onup>207</onup>
							<ondown>207</ondown>
							<onleft>207</onleft>
							<onright>202</onright>
							<include>Common_TVNextAired_FixedList</include>

						</control>
						
					</control>	
						
					<!--Thursday-->
					<control type="group">
						
						<width>1280</width>
						<height>480</height>
						
						<visible>!IsEmpty(Container(203).ListItem(0).Label) + StringCompare(Container(207).Position,3)</visible>
						
						<include>Common_Animation_ShowListing</include>
						
						<control type="fixedlist" id="203">
								
							<onup>207</onup>
							<ondown>207</ondown>
							<onleft>207</onleft>
							<onright>203</onright>
							<include>Common_TVNextAired_FixedList</include>

						</control>
						
					</control>	
						
					<!--Friday-->
					<control type="group">
						
						<width>1280</width>
						<height>480</height>
						
						<visible>!IsEmpty(Container(204).ListItem(0).Label) + StringCompare(Container(207).Position,4)</visible>
						
						<include>Common_Animation_ShowListing</include>
						
						<control type="fixedlist" id="204">
								
							<onup>207</onup>
							<ondown>207</ondown>
							<onleft>207</onleft>
							<onright>204</onright>
							<include>Common_TVNextAired_FixedList</include>

						</control>
						
					</control>	
						
					<!--Saturday-->
					<control type="group">
						
						<width>1280</width>
						<height>480</height>
						
						<visible>!IsEmpty(Container(205).ListItem(0).Label) + StringCompare(Container(207).Position,5)</visible>
						
						<include>Common_Animation_ShowListing</include>
						
						<control type="fixedlist" id="205">
								
							<onup>207</onup>
							<ondown>207</ondown>
							<onleft>207</onleft>
							<onright>205</onright>
							<include>Common_TVNextAired_FixedList</include>

						</control>
						
					</control>	
						
					<!--Sunday-->
					<control type="group">
						
						<width>1280</width>
						<height>480</height>
						
						<visible>!IsEmpty(Container(206).ListItem(0).Label) + StringCompare(Container(207).Position,6)</visible>
						
						<include>Common_Animation_ShowListing</include>
						
						<control type="fixedlist" id="206">
								
							<onup>207</onup>
							<ondown>207</ondown>
							<onleft>207</onleft>
							<onright>206</onright>
							<include>Common_TVNextAired_FixedList</include>

						</control>
						
					</control>
					
				</control>	
				
			</control>
			
			<!--Appbar-->
			<include>Common_AppBar</include>
			
		</control>	
		
	</controls>
	
</window>
